duckyai/__init__.py
duckyai/_hooks/__init__.py
duckyai/_hooks/registration.py
duckyai/_hooks/sdkhooks.py
duckyai/_hooks/types.py
duckyai/_version.py
duckyai/basesdk.py
duckyai/documents.py
duckyai/httpclient.py
duckyai/indexes.py
duckyai/models/__init__.py
duckyai/models/apierror.py
duckyai/models/askindexop.py
duckyai/models/askindexrequest.py
duckyai/models/askindexresponse.py
duckyai/models/askindexresponsesource.py
duckyai/models/batchindextextrequest.py
duckyai/models/createindexrequest.py
duckyai/models/createindexresponse.py
duckyai/models/deletedocumentop.py
duckyai/models/deleteindexop.py
duckyai/models/document.py
duckyai/models/documentindexedresponse.py
duckyai/models/documentretrievedresponse.py
duckyai/models/duckyaierror.py
duckyai/models/errorresponse.py
duckyai/models/getdocumentop.py
duckyai/models/getindexop.py
duckyai/models/getindexresponse.py
duckyai/models/index.py
duckyai/models/indexfile_request.py
duckyai/models/indexmultimodalrequest.py
duckyai/models/indexmultimodalrequestimage.py
duckyai/models/indextextrequest.py
duckyai/models/listdocument.py
duckyai/models/listdocumentsop.py
duckyai/models/listindexesresponse.py
duckyai/models/listpaginateddocumentsresponse.py
duckyai/models/no_response_error.py
duckyai/models/responsevalidationerror.py
duckyai/models/retrievedocumentsrequest.py
duckyai/models/retrievedocumentsresponse.py
duckyai/models/retrievesimilardocumentsrequest.py
duckyai/models/security.py
duckyai/py.typed
duckyai/sdk.py
duckyai/sdkconfiguration.py
duckyai/types/__init__.py
duckyai/types/basemodel.py
duckyai/utils/__init__.py
duckyai/utils/annotations.py
duckyai/utils/datetimes.py
duckyai/utils/enums.py
duckyai/utils/eventstreaming.py
duckyai/utils/forms.py
duckyai/utils/headers.py
duckyai/utils/logger.py
duckyai/utils/metadata.py
duckyai/utils/queryparams.py
duckyai/utils/requestbodies.py
duckyai/utils/retries.py
duckyai/utils/security.py
duckyai/utils/serializers.py
duckyai/utils/unmarshal_json_response.py
duckyai-0.12.0.dist-info/METADATA
duckyai-0.12.0.dist-info/WHEEL
duckyai-0.12.0.dist-info/RECORD
